bkp_core/__init__.py
bkp_core/bkp_conf.py
bkp_core/bkp_mod.py
bkp_core/file_mod.py
bkp_core/fs_mod.py
bkp_core/logger.py
bkp_core/rstr_mod.py
bkp_core/s3_mod.py
bkp_core/ssh_mod.py
bkp_core/stackdump.py
bkp_core/sync_conf.py
bkp_core/sync_mod.py
bkp_core/util.py
bkp_core/version.py
bkp_sync-1.0.1.data/scripts/bkp
bkp_sync-1.0.1.data/scripts/collect
bkp_sync-1.0.1.data/scripts/rstr
bkp_sync-1.0.1.data/scripts/setups3
bkp_sync-1.0.1.data/scripts/sync
bkp_sync-1.0.1.dist-info/LICENSE
bkp_sync-1.0.1.dist-info/METADATA
bkp_sync-1.0.1.dist-info/WHEEL
bkp_sync-1.0.1.dist-info/top_level.txt
bkp_sync-1.0.1.dist-info/RECORD
