Metadata-Version: 2.1
Name: bkp-sync
Version: 1.0.1
Summary: A set of modules and scripts for backing up and syncing files
Home-page: http://github.com/jpfxgood/bkp
Author: James Goodwin
Author-email: bkp-sync@jlgoodwin.com
License: MIT
Keywords: backup,sync
Platform: UNKNOWN
Classifier: Programming Language :: Python :: 3
Classifier: License :: OSI Approved :: MIT License
Classifier: Operating System :: OS Independent
Requires-Python: >=3.6
Requires-Dist: s3cmd
Requires-Dist: paramiko
